{
  "wrapper": "div.landing.landing--home",
  "sections": {
    "d58624ba-3c8d-4fce-94c9-9ed20d9331ec": {
      "type": "lp-23",
      "settings": {
        "backgound_image": "shopify:\/\/shop_images\/TOP_Federal_Hill_Park_-_Harbor_side-MARYLAND-state.jpg",
        "background_color": "#014870",
        "title": "Internet Service Provider in Maryland"
      }
    },
    "fd3ddbf3-dec3-45e4-b386-8fa795d2c243": {
      "type": "lp-2",
      "blocks": {
        "1b94af72-f709-431e-b9d7-413bbcd9be65": {
          "type": "card",
          "settings": {
            "title": "Regular internet with low speed",
            "background_color": "#ffffff",
            "title_color": "#004a6a",
            "image": "shopify:\/\/shop_images\/Infographic_1.png"
          }
        },
        "1f131832-ee5e-44ed-bf7f-729a5bf72a22": {
          "type": "card",
          "settings": {
            "title": "High-speed Internet with Nomad",
            "background_color": "#ffffff",
            "title_color": "#00a77f",
            "image": "shopify:\/\/shop_images\/Infographic_2.png"
          }
        }
      },
      "block_order": [
        "1b94af72-f709-431e-b9d7-413bbcd9be65",
        "1f131832-ee5e-44ed-bf7f-729a5bf72a22"
      ],
      "settings": {
        "title": "Reliable Broadband Internet for Maryland Residents. Do you want to know how it work?"
      }
    },
    "223c3e87-ccd7-435a-a5a9-70bff68c600f": {
      "type": "awesome-tiles-section",
      "blocks": {
        "0e8b0036-362f-4480-81b5-cfb68b1b519c": {
          "type": "card",
          "settings": {
            "image": "shopify:\/\/shop_images\/road-middle-desert-with-magnificent-mountains-california_2_5ed5c62a-2340-4e47-823c-4966e4048c08.jpg",
            "title": "Rural Internet",
            "button_text": "Learn More",
            "button_url": "\/"
          }
        },
        "8f11e89a-3310-4d7b-9273-321c14e5fb95": {
          "type": "card",
          "settings": {
            "image": "shopify:\/\/shop_images\/road-middle-desert-with-magnificent-mountains-california_2_a48d7242-1cf2-4fe0-95de-bed51a03594e.jpg",
            "title": "Travelers & RV Internet",
            "button_text": "Learn More",
            "button_url": "shopify:\/\/pages\/nomad-travel-plan"
          }
        },
        "db130862-0b75-4d5f-be98-c5f6445d7991": {
          "type": "card",
          "settings": {
            "image": "shopify:\/\/shop_images\/road-middle-desert-with-magnificent-mountains-california_2_687ac28a-ec57-44e7-adeb-1e46f47c1108.jpg",
            "title": "Internet for Business",
            "button_text": "Learn More",
            "button_url": "shopify:\/\/pages\/nomad-business-plan"
          }
        },
        "66cf4cc1-3ed8-423d-83f7-d00d80e3a01e": {
          "type": "card",
          "settings": {
            "image": "shopify:\/\/shop_images\/road-middle-desert-with-magnificent-mountains-california_2_24a97137-3c55-40a3-926d-bdd1adc778e8.jpg",
            "title": "Everywhere",
            "button_text": "Learn More",
            "button_url": "shopify:\/\/pages\/plans"
          }
        }
      },
      "block_order": [
        "0e8b0036-362f-4480-81b5-cfb68b1b519c",
        "8f11e89a-3310-4d7b-9273-321c14e5fb95",
        "db130862-0b75-4d5f-be98-c5f6445d7991",
        "66cf4cc1-3ed8-423d-83f7-d00d80e3a01e"
      ],
      "settings": {
        "title": "Why do you need internet in Maryland?",
        "description": "Choose the option that suits you"
      }
    },
    "5e635119-11bf-405e-838e-455861942491": {
      "type": "lp-24",
      "settings": {
        "video": "<iframe width=\"560\" height=\"315\" src=\"https:\/\/www.youtube.com\/embed\/MCHGh74scUY?controls=0\" title=\"YouTube video player\" frameborder=\"0\" allow=\"accelerometer; autoplay; clipboard-write; encrypted-media; gyroscope; picture-in-picture; web-share\" allowfullscreen><\/iframe>",
        "title": "Constant problems with internet speed?",
        "button_text": "Show results",
        "button_url": "shopify:\/\/pages\/reviews"
      }
    },
    "9dbc372e-4301-4a16-b819-cc8ef7044b68": {
      "type": "lp-22",
      "settings": {
        "title": "The most reliable and cost-effective internet provider in Maryland has been identified.",
        "description": "Find your city in Maryland",
        "content": "Aberdeen,\nAnnapolis,\nBaltimore,\nBethesda-Chevy Chase,\nBowie,\nCambridge,\nCatonsville,\nCollege Park,\nColumbia,\nCumberland,\nEaston,\nElkton,\nEmmitsburg,\nFrederick,\nGreenbelt,\nHagerstown,\nHyattsville,\nLaurel,\nOakland,\nOcean City,\nRockville,\nSaint Marys City,\nSalisbury,\nSilver Spring,\nTakoma Park,\nTowson,\nWestminster"
      }
    },
    "9a51b2d4-b777-4c83-9786-db30789ad32c": {
      "type": "awesome-section",
      "blocks": {
        "8f706a9d-8296-4ffe-8574-e023fa7f3aca": {
          "type": "hc-button",
          "settings": {
            "class": "solid",
            "text": "Choose a Plan",
            "url": "shopify:\/\/pages\/plans",
            "blank": false,
            "on_click": ""
          }
        }
      },
      "block_order": [
        "8f706a9d-8296-4ffe-8574-e023fa7f3aca"
      ],
      "settings": {
        "reversed": false,
        "image-as-bg": false,
        "image": "shopify:\/\/shop_images\/BLOG_Maryland_Heights_3-MARYLAND-state.jpg",
        "title_tag": "h2",
        "title": "Staying Productive While Working Remotely in Maryland's Cities",
        "description": "<p>Working remotely can be hard - especially when it comes to staying productive. Fortunately, there are a number of reliable wireless internet services providers which can help remote workers stay connected no matter where their job takes them! Here are some tips on how to make the most out of working remotely in <a href=\"\/pages\/states\" title=\"States\">Maryland<\/a>:<\/p>"
      }
    },
    "f7850f32-f806-4962-b299-b2086ae3af6e": {
      "type": "awesome-text",
      "settings": {
        "heading_size": "2",
        "title_align": "left",
        "columns": "2",
        "heading_text": "",
        "text": "<p>Start your journey in Baltimore and explore one of the many modern coworking spaces located around town. With private offices, high speed internet connections, and fully equipped kitchens - you can easily stay productive while savoring all what Baltimore has to offer. Plus, multiple regional providers also offer reliable High-Speed broadband throughout the city so that staying connected should not be an issue for any remote worker.Head south and experience the beauty of Washington D.C. – boasting multiple coworking spaces perfect for digital nomads looking for some extra space away from their usual desk setup. <\/p>",
        "text_2": "<p>And with Nomad Internet providing unbeatable coverage across rural areas too - regardless if you’re exploring its historic sites or simply working away from home - you’ll always have fast connection speeds at your fingertips! Finally, discover Annapolis and immerse yourself in its cultural diversity while making use of any available coworking spaces located around town. Take advantage of Nomad Internet's wireless internet services to guarantee that remote workers will never have problems managing distractions when they work in <a href=\"https:\/\/nomadinternet.com\/\" title=\"rural areas\">rural areas<\/a> near by as well!<\/p>",
        "text_align": "left"
      }
    },
    "367c5dbd-c419-40cc-903d-0ddc3ead53ef": {
      "type": "lp-15",
      "blocks": {
        "d4c53491-8e07-4c2d-90ce-cea60ce4c82c": {
          "type": "card",
          "settings": {
            "image": "shopify:\/\/shop_images\/21.1.jpg",
            "title": "",
            "url": ""
          }
        },
        "456a8e22-499e-467a-a39b-53b6ea49974d": {
          "type": "card",
          "settings": {
            "image": "shopify:\/\/shop_images\/21.2.jpg",
            "title": "",
            "url": ""
          }
        }
      },
      "block_order": [
        "d4c53491-8e07-4c2d-90ce-cea60ce4c82c",
        "456a8e22-499e-467a-a39b-53b6ea49974d"
      ],
      "settings": {
        "title": "Why is Nomad Internet better than regular internet?",
        "description": ""
      }
    },
    "5fbfc276-398d-4d1f-8003-cbd4d18935cb": {
      "type": "lp-20",
      "blocks": {
        "507fc141-95a1-4874-8db0-2c85e3160ef0": {
          "type": "review",
          "settings": {
            "style": "one",
            "icon": "no",
            "avatar": "shopify:\/\/shop_images\/Dorothy_Barton.jpg",
            "name": "Dorothy Barton",
            "text": "I recently started using nomad internet on a road trip in rural Maryland, and I'm impressed with the service. The speeds are consistently high, no matter where we went, and even with a 4G modem we were able to get enough bandwidth for our streaming needs. I had heard great things about 5G speeds before, but this was even better than expected. For travelers like me, nomad internet is absolutely unbeatable - stable connections that doesn't break down no matter how far away from urban areas you go. Highly recommend!",
            "link": ""
          }
        },
        "ef0c707d-969c-4994-848c-59874ccb048e": {
          "type": "review",
          "settings": {
            "style": "one",
            "icon": "no",
            "avatar": "shopify:\/\/shop_images\/Jessica_Blake.jpg",
            "name": "Jessica Blake",
            "text": "I recently had the chance to try out Nomad Internet on my road trip through rural Maryland, and I was very pleased with the results. Their wireless connection was surprisingly fast and reliable - a huge plus if you're out in the middle of nowhere. My internet worked flawlessly without any hiccups throughout my travels, and I even got decent speeds indoors! All in all, I would highly recommend Nomad Internet for anyone looking for a dependable outdoor internet connection that actually works. No more wondering if your connection will hold up when you’re far away from civilization: Nomad Internet has you covered!",
            "link": ""
          }
        },
        "6127a885-5f5e-4f74-a0d1-ff06e1edbb8a": {
          "type": "review",
          "settings": {
            "style": "one",
            "icon": "no",
            "avatar": "shopify:\/\/shop_images\/Cameron_Mann.jpg",
            "name": "Cameron Mann",
            "text": "I recently went on a road trip to rural Maryland, and I was glad that I had nomad internet with me. This type of outdoor internet is great for travelers who are looking for a reliable connection wherever they go. The connection speeds were much higher than I expected, and my streaming experience was smooth. Overall, the service exceeded my expectations and provided a good value for my money.  If you're looking for an easy-to-use, high-speed internet solution while traveling in remote areas, nomad internet is definitely worth checking out.",
            "link": ""
          }
        },
        "b45f274a-e8ba-4871-b13c-0aada2de689c": {
          "type": "review",
          "settings": {
            "style": "one",
            "icon": "no",
            "avatar": "shopify:\/\/shop_images\/Sylvia_Frost.jpg",
            "name": "Sylvia Frost",
            "text": "I recently had the chance to try out nomad internet while in rural Maryland with friends. It was awesome! We were able to connect our devices easily and have fast, reliable service throughout our camping trip. We used a nomad air modem to make sure we could stay connected, even when we moved around the area. It was great not having to worry about connection issues while sharing stories and making memories with my closest friends. I highly recommend it for anyone looking for an outdoor Internet solution that won't let them down!",
            "link": ""
          }
        },
        "5005d2ab-15ee-4d4a-8ce2-d48e8660400e": {
          "type": "review",
          "settings": {
            "style": "one",
            "icon": "no",
            "avatar": "shopify:\/\/shop_images\/Naomi_Austin.jpg",
            "name": "Naomi Austin",
            "text": "The other day I took a camping trip to rural Maryland with some friends and was surprised by how fast our connection was. The nomad air modem provided an uninterrupted connection that allowed us to stream music, movies, and stay connected with family and friends back home. We didn't have to rely on an inconsistent cell signal which was great since we were in the middle of nowhere. Nomad internet made possible for us to have a carefree, enjoyable experience in the outdoors.",
            "link": ""
          }
        },
        "9641d292-b785-44fb-a588-d0b508e5d17c": {
          "type": "review",
          "settings": {
            "style": "one",
            "icon": "no",
            "avatar": "shopify:\/\/shop_images\/Nadia_Slater.jpg",
            "name": "Nadia Slater",
            "text": "I recently had the opportunity to experience nomad internet in rural Maryland. It was amazing! The fast speeds meant I could connect with friends from all over, even when we were out camping. Setting up the nomad air modem was easy and within minutes we were connected. With so much outdoor fun to be had, knowing that I could get reliable internet was a huge plus. It was great to stay connected without feeling like I was missing out on anything!",
            "link": ""
          }
        }
      },
      "block_order": [
        "507fc141-95a1-4874-8db0-2c85e3160ef0",
        "ef0c707d-969c-4994-848c-59874ccb048e",
        "6127a885-5f5e-4f74-a0d1-ff06e1edbb8a",
        "b45f274a-e8ba-4871-b13c-0aada2de689c",
        "5005d2ab-15ee-4d4a-8ce2-d48e8660400e",
        "9641d292-b785-44fb-a588-d0b508e5d17c"
      ],
      "settings": {
        "title": "Nomad Internet reviews from our site"
      }
    },
    "9ec25f08-c872-440e-96bc-c2f2401b0994": {
      "type": "awesome-html",
      "custom_css": [
        "h2 {font-size: 2em; text-transform: uppercase; margin: 0 auto 1.5em; line-height: 1.3; max-width: 600px;}"
      ],
      "settings": {
        "background-color": "#014870",
        "color": "#ffffff",
        "wide": false,
        "margin_top": 0,
        "margin_bottom": 0,
        "padding-x": 20,
        "padding-y": 50,
        "border-radius": 4,
        "html": "<div class=\"text-center\">\n  <h2>Interested in Learning more about Nomad Internet in your area?<\/h2>\n<div class=\"row v-gutters justify-center\">\n<div class=\"col-auto\">\n<a href=\"tel:+1%20385%20257%202809\" class=\"btn theme\">Call: +1 385 257 2809<\/a>\n<\/div>\n<div class=\"col-auto\">\n<a href=\"javascript:void(0);\" class=\"btn orange\" onclick=\"zE('messenger', 'open');\">Chat Life<\/a>\n<\/div>\n<\/div>\n<\/div>"
      }
    },
    "a5bee9ed-1051-44e6-9e9a-419caa834124": {
      "type": "lp-16",
      "blocks": {
        "09f6ec35-5417-4d9d-8c98-e9b9e105ef27": {
          "type": "block",
          "disabled": true,
          "settings": {
            "title": "Can I use Nomad Internet for RVing?",
            "content": "<p>Nomad Internet users can take the same high-speed, low-latency service they have at home to any location Nomad Internet has coverage. Nomad Internet for RVers\/travelers will allow users to pause and un-pause service based on their individual travel needs.<\/p>"
          }
        },
        "75283694-f9b3-4d88-94c0-18f8290ba571": {
          "type": "block",
          "disabled": true,
          "settings": {
            "title": "Does Nomad Internet have 5G coverage?",
            "content": "<p>Yes, we do.<\/p>"
          }
        },
        "2f7886b7-605c-4d97-8bcd-c1fecd22b66d": {
          "type": "block",
          "disabled": true,
          "settings": {
            "title": "How many WiFi devices can connect to Nomad AIR?",
            "content": "<p>Nomad AIR allows you to connect with up to 30 devices at a time.<\/p>"
          }
        },
        "7dce682e-d232-4c6f-b322-caee417d972c": {
          "type": "block",
          "disabled": true,
          "settings": {
            "title": "How does Nomad Internet’s latency compare to other ISPs?",
            "content": "<p>By using any of our modems, you are guaranteed the lowest latency in the country. Nomad Internet users can expect latency of 20-40ms.<\/p>"
          }
        },
        "12367d20-bb80-43c3-9b1e-eb575ad5bfc7": {
          "type": "block",
          "disabled": true,
          "settings": {
            "title": "Can I use Nomad Modems with a 3rd Party service?",
            "content": "<p>No! We don’t sell modems alone. They must be purchased with a plan. Our Reseller Program is only available to WISPs.<\/p>"
          }
        },
        "33b819aa-9958-4787-b46b-79c56ab710fe": {
          "type": "block",
          "settings": {
            "title": "How can I improve my internet speed in Maryland's rural places?",
            "content": "<p>If you're living in rural Maryland and looking to improve your internet speed, there are several things you can do. Firstly, you can check if your current internet plan offers the maximum speed available in your area. If not, you might want to consider upgrading to a faster plan. <br\/><br\/>Additionally, you could try optimizing your Wi-Fi signal by repositioning your router or investing in a Wi-Fi extender. Another option is to limit the number of devices connected to your network and prioritize your internet usage. <br\/><br\/>Finally, you may want to contact your internet service provider to inquire about any possible network upgrades or improvements that could boost your speed.<\/p>"
          }
        },
        "e56a3c3e-851d-4113-ba4a-501dd8ffc611": {
          "type": "block",
          "settings": {
            "title": "Is 5G available for customers of Nomad Internet in Maryland?",
            "content": "<p>Yes, customers of Nomad Internet in Maryland have access to 5G connectivity.<br\/><br\/>5G is the fifth generation of cellular network technology that offers higher speeds, lower latency, and greater capacity compared to previous generations. It allows for faster downloads and uploads, smoother streaming, and better online gaming experiences. With Nomad Internet's advanced high-power directional antennas in the Nomad Air modem, 5G sub-6GHz and 4G LTE fallback are supported for the perfect balance of network coverage and performance. <br\/><br\/>In addition to 5G connectivity, Nomad Internet offers various tariff plans and modems like the Nomad Air and Nomad Cube, which amplify and accumulate the signal to provide stable and fast internet to all residents of the rural area of Maryland.<\/p>"
          }
        },
        "bd575713-edd6-46ec-b01b-5ee052a4b2d3": {
          "type": "block",
          "settings": {
            "title": "What is the range of internet plans that Nomad Internet offers in Maryland?",
            "content": "<p>Thank you for your interest in Nomad Internet. We offer various internet plans to cater to different needs and preferences. In Maryland, we have three different tariff plans that you can choose from.<br\/><br\/>Our plans are designed to meet various requirements such as browsing the web, streaming videos, online gaming, and working from home. If you're someone who often travels, we have a tariff plan that is suitable for this purpose. Additionally, the number of devices that you want to connect to the internet is also an important consideration when selecting a tariff plan.<br\/><br\/>For businesses with many employees or restaurants that require internet access, we have special rates that are tailored to meet these specific needs. If you're looking for the fastest internet speed possible, we have options available for that as well.<br\/><br\/>We believe that everyone should have access to affordable and reliable internet, regardless of their location. You can find more information about our tariffs and coverage areas on our website. We hope you find the plan that best suits your needs.<\/p>"
          }
        }
      },
      "block_order": [
        "09f6ec35-5417-4d9d-8c98-e9b9e105ef27",
        "75283694-f9b3-4d88-94c0-18f8290ba571",
        "2f7886b7-605c-4d97-8bcd-c1fecd22b66d",
        "7dce682e-d232-4c6f-b322-caee417d972c",
        "12367d20-bb80-43c3-9b1e-eb575ad5bfc7",
        "33b819aa-9958-4787-b46b-79c56ab710fe",
        "e56a3c3e-851d-4113-ba4a-501dd8ffc611",
        "bd575713-edd6-46ec-b01b-5ee052a4b2d3"
      ],
      "settings": {
        "title": "Frequently Asked Questions",
        "button_text": "More Answers",
        "button_url": "https:\/\/support.nomadinternet.com\/"
      }
    },
    "87deca2a-8530-4645-9111-27498b194abd": {
      "type": "lp-25",
      "blocks": {
        "325ce2f5-5cae-4f21-b897-0dfc56fb3994": {
          "type": "card",
          "settings": {
            "image": "shopify:\/\/shop_images\/1_cfb0111f-4f2e-4378-96e9-e28e64c0b7e6.jpg",
            "text": "How to easily exchange and upgrade your Nomad Modem",
            "url": "shopify:\/\/pages\/nomad-trust"
          }
        },
        "575d038c-5c25-4cb8-85ca-d596c50d9717": {
          "type": "card",
          "settings": {
            "image": "shopify:\/\/shop_images\/2_0efdca7d-0144-4fdf-9156-2bf1b61b526e.jpg",
            "text": "Read interesting news about the Internet in your region",
            "url": "shopify:\/\/blogs\/countrynomad"
          }
        },
        "07915a2d-82a8-4c7b-9169-b5f7e1c3dc87": {
          "type": "card",
          "settings": {
            "image": "shopify:\/\/shop_images\/Streaming-2.jpg",
            "text": "Chat and find out about the best Internet providers near you",
            "url": "https:\/\/community.nomadinternet.com\/"
          }
        },
        "1f3bd568-eedc-40c4-a61a-ae1da11224f3": {
          "type": "card",
          "settings": {
            "image": "shopify:\/\/shop_images\/4_0f3659da-d0b6-46be-a82e-05b7a364cb5e.jpg",
            "text": "Download the Nomad Internet mobile app",
            "url": "https:\/\/apps.apple.com\/us\/app\/nomad-internet\/id6444594379"
          }
        }
      },
      "block_order": [
        "325ce2f5-5cae-4f21-b897-0dfc56fb3994",
        "575d038c-5c25-4cb8-85ca-d596c50d9717",
        "07915a2d-82a8-4c7b-9169-b5f7e1c3dc87",
        "1f3bd568-eedc-40c4-a61a-ae1da11224f3"
      ],
      "settings": {
        "title": "Learn more about the Internet that Nomad Internet offers you"
      }
    },
    "242c978b-98d9-42f9-92c4-8d7416d699f9": {
      "type": "lp-16",
      "blocks": {
        "b6465fdb-0b63-4164-9101-089cffe04a02": {
          "type": "block",
          "settings": {
            "title": "What is Nomad Internet?",
            "content": "<p>Nomad Internet is America's largest Wireless Internet Service Provider. We are focused on providing High- Speed wireless Internet to rural communities all over the country and on-the-road travelers!<\/p>"
          }
        },
        "f153998a-0da0-45c2-87f8-460e0b0f771c": {
          "type": "block",
          "settings": {
            "title": "How does Nomad Internet work?",
            "content": "<p>Instead of using traditional Internet wires, we do it by transmitting wireless Internet access directly to your home, business, and even while traveling! We combine the latest technology with Verizon’s service to provide high-speed internet to rural locations and traveling nomads. We offer a variety of internet plans, allowing you to choose one that fits your needs. <\/p>"
          }
        },
        "786d9e04-4a98-4192-8f57-7ddc8bd45fbd": {
          "type": "block",
          "settings": {
            "title": "Do I need to sign a contract to use Nomad Internet?",
            "content": "<p>No contract with Nomad Internet. You get to choose the subscription plan that’s best for you.<\/p>"
          }
        },
        "7ed9d49d-5bf5-45f8-a48d-80eec8faac2d": {
          "type": "block",
          "settings": {
            "title": "Are there data caps?",
            "content": "<p>Yes, all Nomad Internet modems let you use public IPs. Multiple layers of encryption, enhanced Wi-Fi security, firewall filtering, built-in VPN support, IT admin controls, and other features deliver strong security at every level.<\/p>"
          }
        },
        "94382057-d005-40db-9e1c-981fd7bef47b": {
          "type": "block",
          "settings": {
            "title": "Can I use Nomad Internet for gaming?",
            "content": "<p>Yes. Even if you are in the most remote location, we will provide you with robust and reliable internet for all your gaming needs. No matter your plan, you can expect fast internet with low ping rates and latency.<\/p>"
          }
        },
        "29cac46f-3f51-43ca-a8e1-b1da996be9d1": {
          "type": "block",
          "settings": {
            "title": "Can I use Nomad Internet for RVing?",
            "content": "<p>Nomad Internet users can take the same high-speed, low-latency service they have at home to any location Nomad Internet has coverage. Nomad Internet for RVers\/travelers will allow users to pause and un-pause service based on their individual travel needs.<\/p>"
          }
        }
      },
      "block_order": [
        "b6465fdb-0b63-4164-9101-089cffe04a02",
        "f153998a-0da0-45c2-87f8-460e0b0f771c",
        "786d9e04-4a98-4192-8f57-7ddc8bd45fbd",
        "7ed9d49d-5bf5-45f8-a48d-80eec8faac2d",
        "94382057-d005-40db-9e1c-981fd7bef47b",
        "29cac46f-3f51-43ca-a8e1-b1da996be9d1"
      ],
      "settings": {
        "title": "Common Moving Questions",
        "button_text": "More Answers",
        "button_url": "https:\/\/support.nomadinternet.com\/"
      }
    },
    "cfede7e1-184f-4407-b6d6-19d5fa07784e": {
      "type": "lp-21",
      "settings": {
        "title": "You have questions?",
        "description": "You can visit the FAQ page or send your question to us by filling out this form. Our specialists will contact you shortly and answer all your questions.",
        "form_caption": "We guarantee to give answers to your questions."
      }
    },
    "f42db4d5-522d-4d50-95f0-8c169be8d2c2": {
      "type": "awesome-html",
      "custom_css": [
        "h2 {font-size: 50px; line-height: 120%; text-align: center; color: #00a77f; margin: 0;}",
        "h3 {text-align: center; margin: 0; line-height: 120%; font-size: 40px;}",
        ".text {padding: 20px; border-radius: 4px; margin-top: 40px;}"
      ],
      "settings": {
        "background-color": "#ffffff",
        "color": "#111111",
        "wide": false,
        "margin_top": 0,
        "margin_bottom": 0,
        "padding-x": 0,
        "padding-y": 0,
        "border-radius": 0,
        "html": "<h2>Mobility. Speed. Safety. Feel good.<\/h2>\n\n<h3>With Nomad Internet it's a guarantee<\/h3>\n\n<div class=\"text\" style=\"box-shadow: 0 0 8px rgba(0, 0, 0, 0.15)\">\n<p>* Actual speed may vary depending on network activity, configuration and other factors. Subject to availability. Some prices shown may be indicative only. Equipment fees, taxes, and other fees and restrictions may apply.<\/p>\n<\/div>"
      }
    }
  },
  "order": [
    "d58624ba-3c8d-4fce-94c9-9ed20d9331ec",
    "fd3ddbf3-dec3-45e4-b386-8fa795d2c243",
    "223c3e87-ccd7-435a-a5a9-70bff68c600f",
    "5e635119-11bf-405e-838e-455861942491",
    "9dbc372e-4301-4a16-b819-cc8ef7044b68",
    "9a51b2d4-b777-4c83-9786-db30789ad32c",
    "f7850f32-f806-4962-b299-b2086ae3af6e",
    "367c5dbd-c419-40cc-903d-0ddc3ead53ef",
    "5fbfc276-398d-4d1f-8003-cbd4d18935cb",
    "9ec25f08-c872-440e-96bc-c2f2401b0994",
    "a5bee9ed-1051-44e6-9e9a-419caa834124",
    "87deca2a-8530-4645-9111-27498b194abd",
    "242c978b-98d9-42f9-92c4-8d7416d699f9",
    "cfede7e1-184f-4407-b6d6-19d5fa07784e",
    "f42db4d5-522d-4d50-95f0-8c169be8d2c2"
  ]
}