{
  "wrapper": "div.landing.landing--home",
  "sections": {
    "d58624ba-3c8d-4fce-94c9-9ed20d9331ec": {
      "type": "lp-23",
      "settings": {
        "backgound_image": "shopify:\/\/shop_images\/TOP_6_68e0a9a3-c55d-400c-83b6-2426b4391fff.jpg",
        "background_color": "#014870",
        "title": "Internet Service Provider in Vermont"
      }
    },
    "fd3ddbf3-dec3-45e4-b386-8fa795d2c243": {
      "type": "lp-2",
      "blocks": {
        "1b94af72-f709-431e-b9d7-413bbcd9be65": {
          "type": "card",
          "settings": {
            "title": "Regular internet with low speed",
            "background_color": "#ffffff",
            "title_color": "#004a6a",
            "image": "shopify:\/\/shop_images\/Infographic_1.png"
          }
        },
        "1f131832-ee5e-44ed-bf7f-729a5bf72a22": {
          "type": "card",
          "settings": {
            "title": "High-speed Internet with Nomad",
            "background_color": "#ffffff",
            "title_color": "#00a77f",
            "image": "shopify:\/\/shop_images\/Infographic_2.png"
          }
        }
      },
      "block_order": [
        "1b94af72-f709-431e-b9d7-413bbcd9be65",
        "1f131832-ee5e-44ed-bf7f-729a5bf72a22"
      ],
      "settings": {
        "title": "Looking for a secure Internet Service Provider in Vermont? Do you want to know how it work?"
      }
    },
    "223c3e87-ccd7-435a-a5a9-70bff68c600f": {
      "type": "awesome-tiles-section",
      "blocks": {
        "0e8b0036-362f-4480-81b5-cfb68b1b519c": {
          "type": "card",
          "settings": {
            "image": "shopify:\/\/shop_images\/road-middle-desert-with-magnificent-mountains-california_2_5ed5c62a-2340-4e47-823c-4966e4048c08.jpg",
            "title": "Rural Internet",
            "button_text": "Learn More",
            "button_url": "\/"
          }
        },
        "8f11e89a-3310-4d7b-9273-321c14e5fb95": {
          "type": "card",
          "settings": {
            "image": "shopify:\/\/shop_images\/road-middle-desert-with-magnificent-mountains-california_2_a48d7242-1cf2-4fe0-95de-bed51a03594e.jpg",
            "title": "Travelers & RV Internet",
            "button_text": "Learn More",
            "button_url": "shopify:\/\/pages\/nomad-travel-plan"
          }
        },
        "db130862-0b75-4d5f-be98-c5f6445d7991": {
          "type": "card",
          "settings": {
            "image": "shopify:\/\/shop_images\/road-middle-desert-with-magnificent-mountains-california_2_687ac28a-ec57-44e7-adeb-1e46f47c1108.jpg",
            "title": "Internet for Business",
            "button_text": "Learn More",
            "button_url": "shopify:\/\/pages\/nomad-business-plan"
          }
        },
        "66cf4cc1-3ed8-423d-83f7-d00d80e3a01e": {
          "type": "card",
          "settings": {
            "image": "shopify:\/\/shop_images\/road-middle-desert-with-magnificent-mountains-california_2_24a97137-3c55-40a3-926d-bdd1adc778e8.jpg",
            "title": "Everywhere",
            "button_text": "Learn More",
            "button_url": "shopify:\/\/pages\/plans"
          }
        }
      },
      "block_order": [
        "0e8b0036-362f-4480-81b5-cfb68b1b519c",
        "8f11e89a-3310-4d7b-9273-321c14e5fb95",
        "db130862-0b75-4d5f-be98-c5f6445d7991",
        "66cf4cc1-3ed8-423d-83f7-d00d80e3a01e"
      ],
      "settings": {
        "title": "Why do you need internet in Vermont?",
        "description": "Choose the option that suits you"
      }
    },
    "5e635119-11bf-405e-838e-455861942491": {
      "type": "lp-24",
      "settings": {
        "video": "<iframe width=\"560\" height=\"315\" src=\"https:\/\/www.youtube.com\/embed\/mMmhOSJfN4U?controls=0\" title=\"YouTube video player\" frameborder=\"0\" allow=\"accelerometer; autoplay; clipboard-write; encrypted-media; gyroscope; picture-in-picture; web-share\" allowfullscreen><\/iframe>",
        "title": "Constant problems with internet speed?",
        "button_text": "Show results",
        "button_url": "shopify:\/\/pages\/reviews"
      }
    },
    "9dbc372e-4301-4a16-b819-cc8ef7044b68": {
      "type": "lp-22",
      "settings": {
        "title": "The company with the best internet customer experience in Vermont has been identified.",
        "description": "Find your city in Vermont",
        "content": "Barre,\nBellows Falls,\nBennington,\nBrattleboro,\nBurlington,\nEssex,\nManchester,\nMiddlebury,\nMontpelier,\nNewport,\nPlymouth,\nRutland,\nSaint Albans,\nSaint Johnsbury,\nSharon,\nWinooski"
      }
    },
    "9a51b2d4-b777-4c83-9786-db30789ad32c": {
      "type": "awesome-section",
      "blocks": {
        "8f706a9d-8296-4ffe-8574-e023fa7f3aca": {
          "type": "hc-button",
          "settings": {
            "class": "solid",
            "text": "Choose a Plan",
            "url": "shopify:\/\/pages\/plans",
            "blank": false,
            "on_click": ""
          }
        }
      },
      "block_order": [
        "8f706a9d-8296-4ffe-8574-e023fa7f3aca"
      ],
      "settings": {
        "reversed": false,
        "image-as-bg": false,
        "image": "shopify:\/\/shop_images\/BLOG_4_63dcd7a2-8e56-4b5b-849b-e416e3602a86.jpg",
        "title_tag": "h2",
        "title": "The Pros and Cons of Remote Work in Vermont",
        "description": "<p>Working from home has become increasingly popular, especially in today's digital world. But what about remote work in Vermont? This article will explore the pros and cons of working remotely from this beautiful state.One of the most significant pros of remote work in Vermont is that it's a beautiful, peaceful place to work. <\/p>"
      }
    },
    "f7850f32-f806-4962-b299-b2086ae3af6e": {
      "type": "awesome-text",
      "settings": {
        "heading_size": "2",
        "title_align": "left",
        "columns": "2",
        "heading_text": "",
        "text": "<p>From rolling green hills to vibrant foliage, <a href=\"\/pages\/states\" title=\"States\">Vermont<\/a> provides a stunning backdrop for any remote worker. Additionally, there are plenty of outdoor activities available to help you disconnect and recharge after hard days of work. Another pro of working remotely in Vermont is that it's an incredibly affordable place to live. With lower taxes and cost-of- living than many other areas, you'll be able to save money while still enjoying all the beauty that Vermont has to offer. You'll also have access to <a href=\"https:\/\/nomadinternet.com\/\" title=\"high-speed internet providers\">high-speed internet providers<\/a> like Nomad Internet, which can make managing your projects from afar much easier.<\/p>",
        "text_2": "<p>Another key factor to consider when discussing remote work in Vermont is the availability of Nomad Internet. As one of the leading providers of high-speed internet in rural areas, Nomad Internet offers an ideal balance between affordability and reliability. With Nomad Internet, you'll be able to stay connected wherever your work takes you and never miss out on important updates or emails. Plus, you'll enjoy access to fast speeds, consistent service levels, and secure connections – all at a price point that won't break the bank.<\/p><p><\/p>",
        "text_align": "left"
      }
    },
    "367c5dbd-c419-40cc-903d-0ddc3ead53ef": {
      "type": "lp-15",
      "blocks": {
        "d4c53491-8e07-4c2d-90ce-cea60ce4c82c": {
          "type": "card",
          "settings": {
            "image": "shopify:\/\/shop_images\/44.1.jpg",
            "title": "",
            "url": ""
          }
        },
        "456a8e22-499e-467a-a39b-53b6ea49974d": {
          "type": "card",
          "settings": {
            "image": "shopify:\/\/shop_images\/44.2.jpg",
            "title": "",
            "url": ""
          }
        }
      },
      "block_order": [
        "d4c53491-8e07-4c2d-90ce-cea60ce4c82c",
        "456a8e22-499e-467a-a39b-53b6ea49974d"
      ],
      "settings": {
        "title": "Why is Nomad Internet better than regular internet?",
        "description": ""
      }
    },
    "5fbfc276-398d-4d1f-8003-cbd4d18935cb": {
      "type": "lp-20",
      "blocks": {
        "507fc141-95a1-4874-8db0-2c85e3160ef0": {
          "type": "review",
          "settings": {
            "style": "one",
            "icon": "no",
            "avatar": "shopify:\/\/shop_images\/Destiny_Jones.jpg",
            "name": "Destiny Jones",
            "text": "I recently signed up for Nomad Internet, a rural internet provider, and have been impressed with the service. The speeds are fast and reliable with no data caps or usage limits, perfect for streaming and gaming. Best of all, I don't have to commit to any contracts - if something changes in my life I can cancel anytime. And when I had a question their customer service was quick to help me out. All in all, I'm very pleased with the quality of this service!",
            "link": ""
          }
        },
        "ef0c707d-969c-4994-848c-59874ccb048e": {
          "type": "review",
          "settings": {
            "style": "one",
            "icon": "no",
            "avatar": "shopify:\/\/shop_images\/Tracy_Rivera.jpg",
            "name": "Tracy Rivera",
            "text": "I've been using Nomad Internet for the past month and I'm impressed. The speeds are great, even in my rural location, and their no-contract policy is a big plus. The customer service was very helpful when getting set up - they answered all of my questions quickly and clearly. They also offer a 30-day free trial so you can test out the service before committing to it. All things considered, I'm quite pleased with my experience with Nomad Internet so far.",
            "link": ""
          }
        },
        "6127a885-5f5e-4f74-a0d1-ff06e1edbb8a": {
          "type": "review",
          "settings": {
            "style": "one",
            "icon": "no",
            "avatar": "shopify:\/\/shop_images\/Sabrina_Dawson.jpg",
            "name": "Sabrina Dawson",
            "text": "I've been living in rural Vermont with Nomad Internet for a while now and I'm really happy with their service. The speeds are reliable, the unthrottled internet is great, and the no contract policy really works for my needs - no long-term commitment means I can switch to another provider as soon as I find something better (which is highly unlikely). Customer service is friendly and helpful, and they always answer quickly whenever I have a question or need assistance. All in all, Nomad Internet has been a great provider and I'd be happy to recommend them to anyone looking for an affordable and dependable option.",
            "link": ""
          }
        },
        "1de2ac74-3242-4691-92c4-2a9a171afd6d": {
          "type": "review",
          "settings": {
            "style": "one",
            "icon": "no",
            "avatar": "shopify:\/\/shop_images\/Paulina_Sanchez.jpg",
            "name": "Paulina Sanchez",
            "text": "I've been with Nomad Internet for several months now, and I'm very satisfied. Their rural plans are amazing, providing up to unlimited data and high speeds that allow me to do things like working from home and streaming without any lags or buffering. The customer service was quick to answer my questions and made the setup process a breeze. For anyone looking for reliable internet in rural Vermont, I'd definitely recommend giving Nomad Internet a try.",
            "link": ""
          }
        },
        "4f7533b0-ac8d-42b5-8cba-048c0fe3b202": {
          "type": "review",
          "settings": {
            "style": "one",
            "icon": "no",
            "avatar": "shopify:\/\/shop_images\/Audrey_Anderson.jpg",
            "name": "Audrey Anderson",
            "text": "I'm a rural Vermonter and Nomad Internet has been a great service for my area. With unthrottled high-speed internet, I'm able to do all of my online tasks with ease. The customer service is friendly and professional, always ready to answer any of my questions. I especially appreciate the affordable price point that allows me to stay connected without breaking the bank. All in all, it's been an excellent experience and I would happily recommend it.",
            "link": ""
          }
        },
        "65cd53c5-feae-4391-8be2-401adb1bf9f8": {
          "type": "review",
          "settings": {
            "style": "one",
            "icon": "no",
            "avatar": "shopify:\/\/shop_images\/Polly_Cooks.jpg",
            "name": "Polly Cooks",
            "text": "I recently moved to a rural area of Vermont and was pleasantly surprised to find Nomad Internet service. Their internet speeds are unthrottled and fast, making it perfect for online gaming, streaming, and more. I also appreciate the customer service team which is knowledgeable and helpful. The one downside is that the installation process for my area is expensive, but this seems to be common with rural areas. Overall I'm very satisfied with Nomad's reliable high speed internet service!",
            "link": ""
          }
        }
      },
      "block_order": [
        "507fc141-95a1-4874-8db0-2c85e3160ef0",
        "ef0c707d-969c-4994-848c-59874ccb048e",
        "6127a885-5f5e-4f74-a0d1-ff06e1edbb8a",
        "1de2ac74-3242-4691-92c4-2a9a171afd6d",
        "4f7533b0-ac8d-42b5-8cba-048c0fe3b202",
        "65cd53c5-feae-4391-8be2-401adb1bf9f8"
      ],
      "settings": {
        "title": "Nomad Internet reviews from our site"
      }
    },
    "9ec25f08-c872-440e-96bc-c2f2401b0994": {
      "type": "awesome-html",
      "custom_css": [
        "h2 {font-size: 2em; text-transform: uppercase; margin: 0 auto 1.5em; line-height: 1.3; max-width: 600px;}"
      ],
      "settings": {
        "background-color": "#014870",
        "color": "#ffffff",
        "wide": false,
        "margin_top": 0,
        "margin_bottom": 0,
        "padding-x": 20,
        "padding-y": 50,
        "border-radius": 4,
        "html": "<div class=\"text-center\">\n  <h2>Interested in Learning more about Nomad Internet in your area?<\/h2>\n<div class=\"row v-gutters justify-center\">\n<div class=\"col-auto\">\n<a href=\"tel:+1%20385%20257%202809\" class=\"btn theme\">Call: +1 385 257 2809<\/a>\n<\/div>\n<div class=\"col-auto\">\n<a href=\"javascript:void(0);\" class=\"btn orange\" onclick=\"zE('messenger', 'open');\">Chat Life<\/a>\n<\/div>\n<\/div>\n<\/div>"
      }
    },
    "a5bee9ed-1051-44e6-9e9a-419caa834124": {
      "type": "lp-16",
      "blocks": {
        "09f6ec35-5417-4d9d-8c98-e9b9e105ef27": {
          "type": "block",
          "disabled": true,
          "settings": {
            "title": "Can I use Nomad Internet for RVing?",
            "content": "<p>Nomad Internet users can take the same high-speed, low-latency service they have at home to any location Nomad Internet has coverage. Nomad Internet for RVers\/travelers will allow users to pause and un-pause service based on their individual travel needs.<\/p>"
          }
        },
        "75283694-f9b3-4d88-94c0-18f8290ba571": {
          "type": "block",
          "disabled": true,
          "settings": {
            "title": "Does Nomad Internet have 5G coverage?",
            "content": "<p>Yes, we do.<\/p>"
          }
        },
        "2f7886b7-605c-4d97-8bcd-c1fecd22b66d": {
          "type": "block",
          "disabled": true,
          "settings": {
            "title": "How many WiFi devices can connect to Nomad AIR?",
            "content": "<p>Nomad AIR allows you to connect with up to 30 devices at a time.<\/p>"
          }
        },
        "7dce682e-d232-4c6f-b322-caee417d972c": {
          "type": "block",
          "disabled": true,
          "settings": {
            "title": "How does Nomad Internet’s latency compare to other ISPs?",
            "content": "<p>By using any of our modems, you are guaranteed the lowest latency in the country. Nomad Internet users can expect latency of 20-40ms.<\/p>"
          }
        },
        "12367d20-bb80-43c3-9b1e-eb575ad5bfc7": {
          "type": "block",
          "disabled": true,
          "settings": {
            "title": "Can I use Nomad Modems with a 3rd Party service?",
            "content": "<p>No! We don’t sell modems alone. They must be purchased with a plan. Our Reseller Program is only available to WISPs.<\/p>"
          }
        },
        "43dbfe1f-a0e9-4b39-b5c4-1e289359f52d": {
          "type": "block",
          "disabled": true,
          "settings": {
            "title": "What is the best way to improve my rural internet speed in Vermont?",
            "content": "<p>Living in rural Vermont, slow internet speeds can be incredibly frustrating. Fortunately, there are some steps you can take to help improve your internet speed:<\/p><p><strong>Consider switching your current rural internet provider<\/strong> to one that offers fixed wireless service, such as Nomad Internet. This provider offers speeds up to 200 Mbps with plans starting at $99 per month – faster than traditional DSL or dial-up connections.<\/p><p><strong>Make sure your router is positioned in a central location<\/strong> and free from any obstructions that may interfere with the Wi-Fi signal. Place the router away from walls, large pieces of furniture, other electronic devices, and even metal objects as they can absorb the signal and cause it to become weaker over time.<\/p><p><strong>Upgrade your equipment including your Wi-Fi router<\/strong>, modem, and Wi-Fi adapter if necessary. Older or outdated equipment can contribute to slower speeds so consider investing in newer and faster equipment that will provide better performance overall.<\/p><p><strong>Monitor your data usage<\/strong> each month to make sure you aren’t going over any data caps set by your rural internet provider – doing this will ensure that you don’t get penalized for exceeding the limits and that you stay within the boundaries set by them..<\/p><p><strong>Lastly, look into using a signal amplifier such as Nomad Air or Nomad Cube<\/strong> which can boost the signal providing fast and stable internet connection in rural Vermont!<\/p><p>By following these tips and considering providers like Nomad Internet, you can ensure that you have an efficient online experience regardless of how remote your living location is!<\/p>"
          }
        },
        "9503c9ff-14e0-4491-8497-d671f30cf265": {
          "type": "block",
          "disabled": true,
          "settings": {
            "title": "Is there 5G internet available from Nomad Internet in Vermont?",
            "content": "<p>Yes, Nomad Internet offers 5G data plans in Vermont.<br\/><br\/>5G stands for fifth-generation wireless technology and it represents a significant improvement over its predecessor, 4G. 5G networks provide much faster internet speeds, lower latency, and more reliable connections. With 5G, users can download and upload files much faster, stream high-definition videos without buffering, and enjoy online gaming with minimal lag.<br\/><br\/>In Vermont, where rural areas are prevalent, having access to high-speed internet is essential for people to work, learn, and stay connected. Nomad Internet's 5G service utilizes the Nomad Air's advanced high-power directional antennas, which extend the reach of cellular networks, providing fast and reliable internet to residents of rural areas. Additionally, Nomad Internet's 5G service supports 4G LTE fallback, ensuring that customers have the perfect balance of network coverage and performance.<br\/><br\/>Nomad Internet offers various tariff plans to suit different customer needs and budgets. Customers can choose from plans with different speeds and data caps.<br\/><br\/>In conclusion, Nomad Internet provides 5G data plans in Vermont, which offer faster internet speeds, lower latency, and more reliable connections. With Nomad Internet's advanced high-power directional antennas and 4G LTE fallback, residents of rural areas can access fast and reliable internet at an affordable price.<\/p>"
          }
        },
        "0b296d01-e80b-412a-aa4f-494e1881cba1": {
          "type": "block",
          "settings": {
            "title": "What is the best way to improve my rural internet speed in Vermont?",
            "content": "<p>Living in rural Vermont, slow internet speeds can be incredibly frustrating. Fortunately, there are some steps you can take to help improve your internet speed:<\/p><p><strong>Consider switching your current rural internet provider<\/strong> to one that offers fixed wireless service, such as Nomad Internet. This provider offers speeds up to 200 Mbps with plans starting at $99 per month – faster than traditional DSL or dial-up connections.<\/p><p><strong>Make sure your router is positioned in a central location <\/strong>and free from any obstructions that may interfere with the Wi-Fi signal. Place the router away from walls, large pieces of furniture, other electronic devices, and even metal objects as they can absorb the signal and cause it to become weaker over time.<\/p><p><strong>Upgrade your equipment including your Wi-Fi router<\/strong>, modem, and Wi-Fi adapter if necessary. Older or outdated equipment can contribute to slower speeds so consider investing in newer and faster equipment that will provide better performance overall.<\/p><p><strong>Monitor your data usage <\/strong>each month to make sure you aren’t going over any data caps set by your rural internet provider – doing this will ensure that you don’t get penalized for exceeding the limits and that you stay within the boundaries set by them..<\/p><p><strong>Lastly, look into using a signal amplifier such as Nomad Air or Nomad Cube<\/strong> which can boost the signal providing fast and stable internet connection in rural Vermont!<\/p><p>By following these tips and considering providers like Nomad Internet, you can ensure that you have an efficient online experience regardless of how remote your living location is!<\/p>"
          }
        },
        "29344ce0-37fb-483c-9057-faaf53931729": {
          "type": "block",
          "settings": {
            "title": "Is there 5G internet available from Nomad Internet in Vermont?",
            "content": "<p>Yes, Nomad Internet offers 5G data plans in Vermont.<br\/><br\/>5G stands for fifth-generation wireless technology and it represents a significant improvement over its predecessor, 4G. 5G networks provide much faster internet speeds, lower latency, and more reliable connections. With 5G, users can download and upload files much faster, stream high-definition videos without buffering, and enjoy online gaming with minimal lag.<br\/><br\/>In Vermont, where rural areas are prevalent, having access to high-speed internet is essential for people to work, learn, and stay connected. Nomad Internet's 5G service utilizes the Nomad Air's advanced high-power directional antennas, which extend the reach of cellular networks, providing fast and reliable internet to residents of rural areas. Additionally, Nomad Internet's 5G service supports 4G LTE fallback, ensuring that customers have the perfect balance of network coverage and performance.<br\/><br\/>Nomad Internet offers various tariff plans to suit different customer needs and budgets. Customers can choose from plans with different speeds and data caps.<br\/><br\/>In conclusion, Nomad Internet provides 5G data plans in Vermont, which offer faster internet speeds, lower latency, and more reliable connections. With Nomad Internet's advanced high-power directional antennas and 4G LTE fallback, residents of rural areas can access fast and reliable internet at an affordable price.<\/p>"
          }
        }
      },
      "block_order": [
        "09f6ec35-5417-4d9d-8c98-e9b9e105ef27",
        "75283694-f9b3-4d88-94c0-18f8290ba571",
        "2f7886b7-605c-4d97-8bcd-c1fecd22b66d",
        "7dce682e-d232-4c6f-b322-caee417d972c",
        "12367d20-bb80-43c3-9b1e-eb575ad5bfc7",
        "43dbfe1f-a0e9-4b39-b5c4-1e289359f52d",
        "9503c9ff-14e0-4491-8497-d671f30cf265",
        "0b296d01-e80b-412a-aa4f-494e1881cba1",
        "29344ce0-37fb-483c-9057-faaf53931729"
      ],
      "settings": {
        "title": "Frequently Asked Questions",
        "button_text": "More Answers",
        "button_url": "https:\/\/support.nomadinternet.com\/"
      }
    },
    "87deca2a-8530-4645-9111-27498b194abd": {
      "type": "lp-25",
      "blocks": {
        "325ce2f5-5cae-4f21-b897-0dfc56fb3994": {
          "type": "card",
          "settings": {
            "image": "shopify:\/\/shop_images\/1_cfb0111f-4f2e-4378-96e9-e28e64c0b7e6.jpg",
            "text": "How to easily exchange and upgrade your Nomad Modem",
            "url": "shopify:\/\/pages\/nomad-trust"
          }
        },
        "575d038c-5c25-4cb8-85ca-d596c50d9717": {
          "type": "card",
          "settings": {
            "image": "shopify:\/\/shop_images\/2_0efdca7d-0144-4fdf-9156-2bf1b61b526e.jpg",
            "text": "Read interesting news about the Internet in your region",
            "url": "shopify:\/\/blogs\/countrynomad"
          }
        },
        "07915a2d-82a8-4c7b-9169-b5f7e1c3dc87": {
          "type": "card",
          "settings": {
            "image": "shopify:\/\/shop_images\/Streaming-2.jpg",
            "text": "Chat and find out about the best Internet providers near you",
            "url": "https:\/\/community.nomadinternet.com\/"
          }
        },
        "1f3bd568-eedc-40c4-a61a-ae1da11224f3": {
          "type": "card",
          "settings": {
            "image": "shopify:\/\/shop_images\/4_0f3659da-d0b6-46be-a82e-05b7a364cb5e.jpg",
            "text": "Download the Nomad Internet mobile app",
            "url": "https:\/\/apps.apple.com\/us\/app\/nomad-internet\/id6444594379"
          }
        }
      },
      "block_order": [
        "325ce2f5-5cae-4f21-b897-0dfc56fb3994",
        "575d038c-5c25-4cb8-85ca-d596c50d9717",
        "07915a2d-82a8-4c7b-9169-b5f7e1c3dc87",
        "1f3bd568-eedc-40c4-a61a-ae1da11224f3"
      ],
      "settings": {
        "title": "Learn more about the Internet that Nomad Internet offers you"
      }
    },
    "242c978b-98d9-42f9-92c4-8d7416d699f9": {
      "type": "lp-16",
      "blocks": {
        "b6465fdb-0b63-4164-9101-089cffe04a02": {
          "type": "block",
          "settings": {
            "title": "What is Nomad Internet?",
            "content": "<p>Nomad Internet is America's largest Wireless Internet Service Provider. We are focused on providing High- Speed wireless Internet to rural communities all over the country and on-the-road travelers!<\/p>"
          }
        },
        "f153998a-0da0-45c2-87f8-460e0b0f771c": {
          "type": "block",
          "settings": {
            "title": "How does Nomad Internet work?",
            "content": "<p>Instead of using traditional Internet wires, we do it by transmitting wireless Internet access directly to your home, business, and even while traveling! We combine the latest technology with Verizon’s service to provide high-speed internet to rural locations and traveling nomads. We offer a variety of internet plans, allowing you to choose one that fits your needs. <\/p>"
          }
        },
        "786d9e04-4a98-4192-8f57-7ddc8bd45fbd": {
          "type": "block",
          "settings": {
            "title": "Do I need to sign a contract to use Nomad Internet?",
            "content": "<p>No contract with Nomad Internet. You get to choose the subscription plan that’s best for you.<\/p>"
          }
        },
        "7ed9d49d-5bf5-45f8-a48d-80eec8faac2d": {
          "type": "block",
          "settings": {
            "title": "Are there data caps?",
            "content": "<p>Yes, all Nomad Internet modems let you use public IPs. Multiple layers of encryption, enhanced Wi-Fi security, firewall filtering, built-in VPN support, IT admin controls, and other features deliver strong security at every level.<\/p>"
          }
        },
        "94382057-d005-40db-9e1c-981fd7bef47b": {
          "type": "block",
          "settings": {
            "title": "Can I use Nomad Internet for gaming?",
            "content": "<p>Yes. Even if you are in the most remote location, we will provide you with robust and reliable internet for all your gaming needs. No matter your plan, you can expect fast internet with low ping rates and latency.<\/p>"
          }
        },
        "29cac46f-3f51-43ca-a8e1-b1da996be9d1": {
          "type": "block",
          "settings": {
            "title": "Can I use Nomad Internet for RVing?",
            "content": "<p>Nomad Internet users can take the same high-speed, low-latency service they have at home to any location Nomad Internet has coverage. Nomad Internet for RVers\/travelers will allow users to pause and un-pause service based on their individual travel needs.<\/p>"
          }
        }
      },
      "block_order": [
        "b6465fdb-0b63-4164-9101-089cffe04a02",
        "f153998a-0da0-45c2-87f8-460e0b0f771c",
        "786d9e04-4a98-4192-8f57-7ddc8bd45fbd",
        "7ed9d49d-5bf5-45f8-a48d-80eec8faac2d",
        "94382057-d005-40db-9e1c-981fd7bef47b",
        "29cac46f-3f51-43ca-a8e1-b1da996be9d1"
      ],
      "settings": {
        "title": "Common Moving Questions",
        "button_text": "More Answers",
        "button_url": "https:\/\/support.nomadinternet.com\/"
      }
    },
    "cfede7e1-184f-4407-b6d6-19d5fa07784e": {
      "type": "lp-21",
      "settings": {
        "title": "You have questions?",
        "description": "You can visit the FAQ page or send your question to us by filling out this form. Our specialists will contact you shortly and answer all your questions.",
        "form_caption": "We guarantee to give answers to your questions."
      }
    },
    "f42db4d5-522d-4d50-95f0-8c169be8d2c2": {
      "type": "awesome-html",
      "custom_css": [
        "h2 {font-size: 50px; line-height: 120%; text-align: center; color: #00a77f; margin: 0;}",
        "h3 {text-align: center; margin: 0; line-height: 120%; font-size: 40px;}",
        ".text {padding: 20px; border-radius: 4px; margin-top: 40px;}"
      ],
      "settings": {
        "background-color": "#ffffff",
        "color": "#111111",
        "wide": false,
        "margin_top": 0,
        "margin_bottom": 0,
        "padding-x": 0,
        "padding-y": 0,
        "border-radius": 0,
        "html": "<h2>Mobility. Speed. Safety. Feel good.<\/h2>\n\n<h3>With Nomad Internet it's a guarantee<\/h3>\n\n<div class=\"text\" style=\"box-shadow: 0 0 8px rgba(0, 0, 0, 0.15)\">\n<p>* Actual speed may vary depending on network activity, configuration and other factors. Subject to availability. Some prices shown may be indicative only. Equipment fees, taxes, and other fees and restrictions may apply.<\/p>\n<\/div>"
      }
    }
  },
  "order": [
    "d58624ba-3c8d-4fce-94c9-9ed20d9331ec",
    "fd3ddbf3-dec3-45e4-b386-8fa795d2c243",
    "223c3e87-ccd7-435a-a5a9-70bff68c600f",
    "5e635119-11bf-405e-838e-455861942491",
    "9dbc372e-4301-4a16-b819-cc8ef7044b68",
    "9a51b2d4-b777-4c83-9786-db30789ad32c",
    "f7850f32-f806-4962-b299-b2086ae3af6e",
    "367c5dbd-c419-40cc-903d-0ddc3ead53ef",
    "5fbfc276-398d-4d1f-8003-cbd4d18935cb",
    "9ec25f08-c872-440e-96bc-c2f2401b0994",
    "a5bee9ed-1051-44e6-9e9a-419caa834124",
    "87deca2a-8530-4645-9111-27498b194abd",
    "242c978b-98d9-42f9-92c4-8d7416d699f9",
    "cfede7e1-184f-4407-b6d6-19d5fa07784e",
    "f42db4d5-522d-4d50-95f0-8c169be8d2c2"
  ]
}